intercomic/__init__.py
intercomic/client.py
intercomic-0.1.1.dist-info/DESCRIPTION.rst
intercomic-0.1.1.dist-info/METADATA
intercomic-0.1.1.dist-info/RECORD
intercomic-0.1.1.dist-info/WHEEL
intercomic-0.1.1.dist-info/metadata.json
intercomic-0.1.1.dist-info/top_level.txt
