Metadata-Version: 2.0
Name: intercomic
Version: 0.1.1
Summary: Tiny REST API Client for intercom.io
Home-page: http://github.com/kidig/intercomic
Author: Dmitrii Gerasimenko
Author-email: kiddima@gmail.com
License: MIT
Keywords: intercom,api
Platform: UNKNOWN
Classifier: Development Status :: 4 - Beta
Classifier: Intended Audience :: Developers
Classifier: License :: OSI Approved :: MIT License
Classifier: Operating System :: OS Independent
Classifier: Programming Language :: Python
Classifier: Programming Language :: Python :: 3.5
Classifier: Programming Language :: Python :: 3.6
Classifier: Topic :: Software Development :: Libraries :: Python Modules
Requires-Dist: requests
